handygenome/__init__.py
handygenome/bameditor.py
handygenome/blacklist.py
handygenome/cosmic_download.py
handygenome/deco.py
handygenome/fastahandler.py
handygenome/gatk.py
handygenome/hgvs.py
handygenome/igvhandle.py
handygenome/interval.py
handygenome/logutils.py
handygenome/methylation.py
handygenome/network.py
handygenome/peakutils.py
handygenome/pyranges_helper.py
handygenome/sequtils.py
handygenome/tools.py
handygenome/ucscdata.py
handygenome/align/__init__.py
handygenome/align/alignhandler.py
handygenome/align/msa.py
handygenome/align/pairwise.py
handygenome/align/realign_legacy_pysampileup_mypileup_comparison.py
handygenome/align/realign_using_fetchedreads.py
handygenome/align/toolwrapper.py
handygenome/align/realign/base.py
handygenome/align/realign/msrpileup.py
handygenome/align/realign/msrpileup_series.py
handygenome/align/realign/rpileup.py
handygenome/align/realign/rpileup_series.py
handygenome/analysis/__init__.py
handygenome/analysis/driver.py
handygenome/analysis/feature.py
handygenome/annotation/__init__.py
handygenome/annotation/annotitem.py
handygenome/annotation/annotitem_deprecated.py
handygenome/annotation/callerinfo.py
handygenome/annotation/cosmic.py
handygenome/annotation/customfile.py
handygenome/annotation/customfile_deprecated.py
handygenome/annotation/data.py
handygenome/annotation/ensembl_feature.py
handygenome/annotation/ensembl_parser.py
handygenome/annotation/ensembl_parser_deprecated.py
handygenome/annotation/ensembl_rest.py
handygenome/annotation/feature.py
handygenome/annotation/genotype.py
handygenome/annotation/oncokb.py
handygenome/annotation/popfreq.py
handygenome/annotation/readstats.py
handygenome/annotation/rnalib.py
handygenome/annotation/veplib.py
handygenome/bin/__init__.py
handygenome/bin/alleleindex_annotator.py
handygenome/bin/annotate_feature.py
handygenome/bin/annotate_readstats.py
handygenome/bin/bismark_to_vcf.py
handygenome/bin/caller_postprocessor.py
handygenome/bin/concat_vcf.py
handygenome/bin/merge_vcf.py
handygenome-0.4.6.dist-info/LICENSE.txt
handygenome-0.4.6.dist-info/METADATA
handygenome-0.4.6.dist-info/WHEEL
handygenome-0.4.6.dist-info/entry_points.txt
handygenome-0.4.6.dist-info/top_level.txt
handygenome-0.4.6.dist-info/RECORD
