Metadata-Version: 2.1
Name: handygenome
Version: 0.4.6
Summary: An integrated platform for genome sequencing analysis
Author-email: Ji-Hyung Park <p69180@gmail.com>
Project-URL: Documentation, https://handygenome.readthedocs.io/en/latest/
Project-URL: Repository, https://github.com/p69180/handygenome.git
Classifier: Programming Language :: Python :: 3
Classifier: License :: OSI Approved :: MIT License
Classifier: Operating System :: OS Independent
Requires-Python: >=3.10
License-File: LICENSE.txt
Requires-Dist: numpy
Requires-Dist: pandas
Requires-Dist: matplotlib
Requires-Dist: biopython >=1.80
Requires-Dist: pysam
Requires-Dist: pyranges
Requires-Dist: scipy
Requires-Dist: scikit-learn
Requires-Dist: PyYAML
Requires-Dist: jupyterlab
